ghosttag/__init__.py
ghosttag/core.py
ghosttag_steganography-0.1.0.dist-info/METADATA
ghosttag_steganography-0.1.0.dist-info/WHEEL
ghosttag_steganography-0.1.0.dist-info/top_level.txt
ghosttag_steganography-0.1.0.dist-info/RECORD
