Metadata-Version: 2.4
Name: ghosttag-steganography
Version: 0.1.0
Summary: Error-Corrected Steganography for Lossy Environments
Author-email: Tirthik <tirthikdurgam04@gmail.com>
License: MIT
Project-URL: Homepage, https://github.com/tirthikdurgam/ghosttag
Project-URL: Bug Tracker, https://github.com/tirthikdurgam/ghosttag/issues
Classifier: Programming Language :: Python :: 3
Classifier: License :: OSI Approved :: MIT License
Classifier: Topic :: Security :: Cryptography
Classifier: Topic :: Multimedia :: Graphics
Classifier: Operating System :: OS Independent
Requires-Python: >=3.7
Requires-Dist: Pillow>=9.0.0
Requires-Dist: numpy>=1.21.0
Requires-Dist: reedsolo>=1.5.0
